pyrnp/__init__.py
pyrnp/client.py
pyrnp/exception.py
pyrnp/util.py
pyrnp-1.1.3.dist-info/LICENSE
pyrnp-1.1.3.dist-info/METADATA
pyrnp-1.1.3.dist-info/WHEEL
pyrnp-1.1.3.dist-info/top_level.txt
pyrnp-1.1.3.dist-info/RECORD
