Metadata-Version: 2.1
Name: pyrnp
Version: 1.1.3
Summary: Python client library for Eduplay (video platform from RNP)
Home-page: https://github.com/cnpem-iot/pyrnp
Author: Guilherme F. de Freitas
Author-email: g.fr@tuta.io
License: GNU Affero General Public License v3 or later (AGPLv3+)
Platform: any
Classifier: Development Status :: 4 - Beta
Classifier: Intended Audience :: Developers
Classifier: Topic :: Software Development :: Build Tools
Classifier: License :: OSI Approved :: GNU Affero General Public License v3 or later (AGPLv3+)
Classifier: Natural Language :: English
Classifier: Environment :: Web Environment
Classifier: Programming Language :: Python :: 3
Classifier: Programming Language :: Python :: 3.6
Classifier: Programming Language :: Python :: 3.7
Classifier: Programming Language :: Python :: 3.8
Classifier: Programming Language :: Python :: 3.9
Classifier: Programming Language :: Python :: 3 :: Only
Classifier: Operating System :: OS Independent
Classifier: Topic :: Internet
Classifier: Topic :: Office/Business
Classifier: Topic :: Software Development :: Libraries
License-File: LICENSE
Requires-Dist: requests
